lite/__init__.py
lite/app.py
lite/cli.py
lite/core/__init__.py
lite/core/lite.backup.py
lite/core/lite.py
lite/core/controller/__init__.py
lite/core/request/__init__.py
lite/core/response/__init__.py
lite/core/router/__init__.py
lite/core/session/__init__.py
lite/core/view/__init__.py
lite/fascade/__init__.py
lite_gs-0.1.2.dist-info/LICENCE
lite_gs-0.1.2.dist-info/METADATA
lite_gs-0.1.2.dist-info/WHEEL
lite_gs-0.1.2.dist-info/entry_points.txt
lite_gs-0.1.2.dist-info/top_level.txt
lite_gs-0.1.2.dist-info/RECORD
